[{
    "Name": "Iconify",
    "Version": "1.5",
    "Release": "March 11, 2018",
    "Current": "September 2, 2018",
    "Language": ["C#"],
    "Category": ["Utilities"],
    "Image": "img/iconify.png",
    "Button1Text": "GitHub",
    "Button1Link": "https://github.com/the404devs/iconify",
    "Description": "Open an image, and this will convert it into an icon file you can use on webpages, programs, etc. I actually use this thing all the time, pretty much every program I've made from this point on has an icon made with this program.<br><br><b>v1.5 (09/02/18):</b> Updated to match new 404 colour scheme."
}]